nuasa_election_admin/__init__.py
nuasa_election_admin/main.py
nuasa_election_admin-0.1.0.dist-info/entry_points.txt
nuasa_election_admin-0.1.0.dist-info/METADATA
nuasa_election_admin-0.1.0.dist-info/WHEEL
nuasa_election_admin-0.1.0.dist-info/RECORD
