Metadata-Version: 2.1
Name: nuasa-election-admin
Version: 0.1.0
Summary: Administration command line for nuasa election portal
Author: Ini-abasi
Author-email: etimi531@gmail.com
Requires-Python: >=3.11,<4.0
Classifier: Programming Language :: Python :: 3
Classifier: Programming Language :: Python :: 3.11
Requires-Dist: typer[all] (>=0.9.0,<0.10.0)
